[{"testset":{"tests":[{"testcase":{"tag":"@organizations_navigation_to_explore_organizations_0001","time":"2019-06-14 11:56:12","title":"Navigation to context 'Explore Organizations'","steps":[{"date":"2019-06-14 11:56:12","substeps":[{"date":"2019-06-14 11:56:38","message":"&quot;SignInPage&quot; was loaded successfully","status":"passed"},{"date":"2019-06-14 11:56:39","message":"Clear Textbox_Email_address.","status":"passed"},{"date":"2019-06-14 11:56:39","message":"Textbox_Email_address  cleared.","status":"passed"},{"date":"2019-06-14 11:56:39","message":"Text of Textbox_Email_address is .","status":"passed"},{"date":"2019-06-14 11:56:39","message":"Text of Textbox_Email_address is dinesh.p@clarivate.com.","status":"passed"},{"date":"2019-06-14 11:56:39","message":"Textbox_Email_address  'dinesh.p@clarivate.com' text was entered.","status":"passed"},{"date":"2019-06-14 11:56:39","message":"Clear Textbox_Password.","status":"passed"},{"date":"2019-06-14 11:56:39","message":"Textbox_Password  cleared.","status":"passed"},{"date":"2019-06-14 11:56:39","message":"Text of Textbox_Password is .","status":"passed"},{"date":"2019-06-14 11:56:39","message":"Text of Textbox_Password is @321DIN#.","status":"passed"},{"date":"2019-06-14 11:56:39","message":"Textbox_Password  '@321DIN#' text was entered.","status":"passed"},{"date":"2019-06-14 11:56:44","message":"Button_Login was clicked.","status":"passed"},{"date":"2019-06-14 11:56:48","message":"isDisplayed of Modal_Dialog : false.","status":"passed"},{"date":"2019-06-14 11:56:48","message":"&quot;AnaliticsPage&quot; was loaded successfully","status":"passed"}],"title":"I am logged in to application","status":"passed"},{"date":"2019-06-14 11:56:12","substeps":[{"date":"2019-06-14 11:56:49","message":"Button_Organizations was clicked.","status":"passed"},{"date":"2019-06-14 11:56:55","message":"&quot;AnaliticsPage&quot; was loaded successfully","status":"passed"}],"title":"I have clicked on icon &quot;Organizations&quot; on page 'Analytics Landing Page'","status":"passed"},{"date":"2019-06-14 11:56:12","substeps":[{"date":"2019-06-14 11:57:10","message":"isDisplayed of Container_CreateNewTile : true.","status":"passed"},{"date":"2019-06-14 11:57:10","message":"isDisplayed of Container_CreateNewTile : true.","status":"passed"},{"date":"2019-06-14 11:57:10","message":"isDisplayed of Container_CreateNewTile : true.","status":"passed"},{"date":"2019-06-14 11:57:10","message":"Page 'Explore People' was displayed","status":"passed"},{"date":"2019-06-14 11:57:10","message":"isDisplayed of initHTMLContainers : true.","status":"passed"},{"date":"2019-06-14 11:57:10","message":"isDisplayed of initHTMLContainers : true.","status":"passed"},{"date":"2019-06-14 11:57:10","message":"isDisplayed of initHTMLContainers : true.","status":"passed"},{"date":"2019-06-14 11:57:10","message":"Page 'Explore People' was displayed","status":"passed"}],"title":"Page 'Explore Organizations' is displayed","status":"passed"}],"status":"passed"}}],"os":"Windows 10 10.0 amd64","ip":"10.10.247.155","browser":"firefox","name":"Feature_OrganizationsNavigationToOrgContext","time":"2019-06-14 11:56:12","url":"https://incites.qa2.dev-incites.com","targettestcycle":"IC2.62 Release"}}]