[{"testset":{"tests":[{"testcase":{"tag":"@Basic_Structure_001","time":"2019-06-14 23:22:27","title":"001) On clicking the plus sign an accordion will open","steps":[{"date":"2019-06-14 23:23:07","substeps":[{"date":"2019-06-14 23:23:07","message":"Logged in with user: 'RegressionFullUser7@clarivate.com","status":"passed"},{"date":"2019-06-14 23:23:48","message":"New Home page logged in  properly","status":"passed"}],"title":"the &quot;New Home&quot; page should be loaded on log on","status":"passed"},{"date":"2019-06-14 23:23:48","substeps":[{"date":"2019-06-14 23:23:48","message":"6 accordion arepresent","status":"passed"}],"title":"I verify 6 accordion are displays","status":"passed"},{"date":"2019-06-14 23:23:49","substeps":[{"date":"2019-06-14 23:23:49","message":"Accordion Collapse is working fine","status":"passed"}],"title":"I collapse &quot;All&quot; Accordion in Home Page","status":"passed"},{"date":"2019-06-14 23:23:49","substeps":[{"date":"2019-06-14 23:23:49","message":"All Accordion are  closed","status":"passed"}],"title":"I verify &quot;All&quot; the Accordions in Home page are closed","status":"passed"},{"date":"2019-06-14 23:24:20","substeps":[{"date":"2019-06-14 23:24:20","message":"Accordion Expand is working fine","status":"passed"}],"title":"I expand &quot;All&quot; Accordion in Home Page","status":"passed"},{"date":"2019-06-14 23:24:26","substeps":[{"date":"2019-06-14 23:24:26","message":"[All] Accordion Open","status":"passed"}],"title":"I verify &quot;All&quot; the Accordions in Home page are open","status":"passed"},{"date":"2019-06-14 23:24:27","substeps":[{"date":"2019-06-14 23:24:27","message":"Accordion Collapse is working fine","status":"passed"}],"title":"I collapse &quot;All&quot; Accordion in Home Page","status":"passed"}],"status":"passed"}},{"testcase":{"tag":"@Basic_Structure_002","time":"2019-06-14 23:24:46","title":"002) On clicking a minus sign an accordion will close","steps":[{"date":"2019-06-14 23:25:26","substeps":[{"date":"2019-06-14 23:25:26","message":"Logged in with user: 'RegressionFullUser7@clarivate.com","status":"passed"},{"date":"2019-06-14 23:26:08","message":"New Home page logged in  properly","status":"passed"}],"title":"the &quot;New Home&quot; page should be loaded on log on","status":"passed"},{"date":"2019-06-14 23:26:40","substeps":[{"date":"2019-06-14 23:26:40","message":"Accordion Expand is working fine","status":"passed"}],"title":"I expand &quot;All&quot; Accordion in Home Page","status":"passed"},{"date":"2019-06-14 23:26:45","substeps":[{"date":"2019-06-14 23:26:45","message":"[All] Accordion Open","status":"passed"}],"title":"I verify &quot;All&quot; the Accordions in Home page are open","status":"passed"},{"date":"2019-06-14 23:26:46","substeps":[{"date":"2019-06-14 23:26:46","message":"Accordion Collapse is working fine","status":"passed"}],"title":"I collapse &quot;All&quot; Accordion in Home Page","status":"passed"},{"date":"2019-06-14 23:26:47","substeps":[{"date":"2019-06-14 23:26:47","message":"All Accordion are  closed","status":"passed"}],"title":"I verify &quot;All&quot; the Accordions in Home page are closed","status":"passed"}],"status":"passed"}},{"testcase":{"tag":"@Basic_Structure_003","time":"2019-06-14 23:27:05","title":"003) If there are more than one accordion then up and down arrows will be shown","steps":[{"date":"2019-06-14 23:27:45","substeps":[{"date":"2019-06-14 23:27:45","message":"Logged in with user: 'RegressionFullUser7@clarivate.com","status":"passed"},{"date":"2019-06-14 23:28:26","message":"New Home page logged in  properly","status":"passed"}],"title":"the &quot;New Home&quot; page should be loaded on log on","status":"passed"},{"date":"2019-06-14 23:28:26","substeps":[{"date":"2019-06-14 23:28:26","message":"More than 2 accordion are Available","status":"passed"}],"title":"I verify two or more Accordions are present in Home Page for the user","status":"passed"},{"date":"2019-06-14 23:28:47","substeps":[{"date":"2019-06-14 23:28:47","message":"More than 2 accordion are Available","status":"passed"}],"title":"I verify that 'up' and 'down' arrows are present for the accordions","status":"passed"}],"status":"passed"}},{"testcase":{"tag":"@Basic_Structure_004","time":"2019-06-14 23:29:09","title":"004)  The top accordion will have a down arrow only","steps":[{"date":"2019-06-14 23:29:52","substeps":[{"date":"2019-06-14 23:29:52","message":"Logged in with user: 'RegressionFullUser7@clarivate.com","status":"passed"},{"date":"2019-06-14 23:30:35","message":"New Home page logged in  properly","status":"passed"}],"title":"the &quot;New Home&quot; page should be loaded on log on","status":"passed"},{"date":"2019-06-14 23:30:35","substeps":[{"date":"2019-06-14 23:30:35","message":"More than 2 accordion are Available","status":"passed"}],"title":"I verify two or more Accordions are present in Home Page for the user","status":"passed"},{"date":"2019-06-14 23:30:41","substeps":[{"date":"2019-06-14 23:30:41","message":"Top Accordion up/down Arrow are correct","status":"passed"}],"title":"I verify only 'down' arrow is present for the top Accordion","status":"passed"}],"status":"passed"}},{"testcase":{"tag":"@Basic_Structure_005","time":"2019-06-14 23:31:02","title":"005) The bottom accordion will have a up arrow only","steps":[{"date":"2019-06-14 23:31:42","substeps":[{"date":"2019-06-14 23:31:42","message":"Logged in with user: 'RegressionFullUser7@clarivate.com","status":"passed"},{"date":"2019-06-14 23:32:23","message":"New Home page logged in  properly","status":"passed"}],"title":"the &quot;New Home&quot; page should be loaded on log on","status":"passed"},{"date":"2019-06-14 23:32:23","substeps":[{"date":"2019-06-14 23:32:23","message":"More than 2 accordion are Available","status":"passed"}],"title":"I verify two or more Accordions are present in Home Page for the user","status":"passed"},{"date":"2019-06-14 23:32:28","substeps":[{"date":"2019-06-14 23:32:28","message":"Bottom Accordion up/down Arrow are correct","status":"passed"}],"title":"I verify only 'up' arrow is present for the bottom Accordion","status":"passed"}],"status":"passed"}},{"testcase":{"tag":"@Basic_Structure_006","time":"2019-06-14 23:32:48","title":"006) verify the presence of 'PlaceHolder' inside the accordion","steps":[{"date":"2019-06-14 23:33:27","substeps":[{"date":"2019-06-14 23:33:27","message":"Logged in with user: 'RegressionFullUser7@clarivate.com","status":"passed"},{"date":"2019-06-14 23:34:09","message":"New Home page logged in  properly","status":"passed"}],"title":"the &quot;New Home&quot; page should be loaded on log on","status":"passed"},{"date":"2019-06-14 23:34:29","substeps":[{"date":"2019-06-14 23:34:29","message":"Accordion Expand is working fine","status":"passed"}],"title":"I expand &quot;Competitive intelligence&quot; Accordion in Home Page","status":"passed"},{"date":"2019-06-14 23:34:29","substeps":[{"date":"2019-06-14 23:34:29","message":"[Competitive intelligence] Accordion Open","status":"passed"}],"title":"I verify &quot;Competitive intelligence&quot; the Accordions in Home page are open","status":"passed"},{"date":"2019-06-14 23:34:29","substeps":[{"date":"2019-06-14 23:34:29","message":"Place Holder are exact","status":"passed"}],"title":"I verify the placeholders are present for &quot;Competitive intelligence&quot; accordion","status":"passed"},{"date":"2019-06-14 23:34:49","substeps":[{"date":"2019-06-14 23:34:49","message":"Accordion Expand is working fine","status":"passed"}],"title":"I expand &quot;Clinical Trials intelligence&quot; Accordion in Home Page","status":"passed"},{"date":"2019-06-14 23:34:49","substeps":[{"date":"2019-06-14 23:34:49","message":"[Clinical Trials intelligence] Accordion Open","status":"passed"}],"title":"I verify &quot;Clinical Trials intelligence&quot; the Accordions in Home page are open","status":"passed"},{"date":"2019-06-14 23:34:49","substeps":[{"date":"2019-06-14 23:34:49","message":"Place Holder are exact","status":"passed"}],"title":"I verify the placeholders are present for &quot;Clinical trials intelligence&quot; accordion","status":"passed"},{"date":"2019-06-14 23:35:10","substeps":[{"date":"2019-06-14 23:35:10","message":"Accordion Expand is working fine","status":"passed"}],"title":"I expand &quot;Deals intelligence&quot; Accordion in Home Page","status":"passed"},{"date":"2019-06-14 23:35:10","substeps":[{"date":"2019-06-14 23:35:10","message":"[Deals intelligence] Accordion Open","status":"passed"}],"title":"I verify &quot;Deals intelligence&quot; the Accordions in Home page are open","status":"passed"},{"date":"2019-06-14 23:35:10","substeps":[{"date":"2019-06-14 23:35:10","message":"Place Holder are exact","status":"passed"}],"title":"I verify the placeholders are present for &quot;Deals intelligence&quot; accordion","status":"passed"},{"date":"2019-06-14 23:35:30","substeps":[{"date":"2019-06-14 23:35:30","message":"Accordion Expand is working fine","status":"passed"}],"title":"I expand &quot;Regulatory intelligence&quot; Accordion in Home Page","status":"passed"},{"date":"2019-06-14 23:35:30","substeps":[{"date":"2019-06-14 23:35:30","message":"[Regulatory intelligence] Accordion Open","status":"passed"}],"title":"I verify &quot;Regulatory intelligence&quot; the Accordions in Home page are open","status":"passed"},{"date":"2019-06-14 23:35:30","substeps":[{"date":"2019-06-14 23:35:30","message":"Place Holder are exact","status":"passed"}],"title":"I verify the placeholders are present for &quot;Regulatory intelligence&quot; accordion","status":"passed"},{"date":"2019-06-14 23:35:51","substeps":[{"date":"2019-06-14 23:35:51","message":"Accordion Expand is working fine","status":"passed"}],"title":"I expand &quot;Disease Briefings&quot; Accordion in Home Page","status":"passed"},{"date":"2019-06-14 23:35:51","substeps":[{"date":"2019-06-14 23:35:51","message":"[Disease Briefings] Accordion Open","status":"passed"}],"title":"I verify &quot;Disease Briefings&quot; the Accordions in Home page are open","status":"passed"},{"date":"2019-06-14 23:35:51","substeps":[{"date":"2019-06-14 23:35:51","message":"Place Holder are exact","status":"passed"}],"title":"I verify the placeholders are present for &quot;Disease Briefings&quot; accordion","status":"passed"},{"date":"2019-06-14 23:36:11","substeps":[{"date":"2019-06-14 23:36:11","message":"Accordion Expand is working fine","status":"passed"}],"title":"I expand &quot;News&quot; Accordion in Home Page","status":"passed"},{"date":"2019-06-14 23:36:11","substeps":[{"date":"2019-06-14 23:36:11","message":"[News] Accordion Open","status":"passed"}],"title":"I verify &quot;News&quot; the Accordions in Home page are open","status":"passed"},{"date":"2019-06-14 23:36:11","substeps":[{"date":"2019-06-14 23:36:11","message":"Place Holder are exact","status":"passed"}],"title":"I verify the placeholders are present for &quot;News&quot; accordion","status":"passed"}],"status":"passed"}}],"os":"Windows Server 2008 R2 6.1 x86","ip":"10.152.83.165","browser":"chrome","name":"Feature_HomePage_BasicStructure","time":"2019-06-14 23:22:27","url":"https://stable.cortellis.int.clarivate.com","targettestcycle":"Regression_14_June_2019"}}]