[{"testset":{"tests":[{"testcase":{"tag":"@CCIssue_22","time":"2019-03-07 17:50:43","title":"DII - Saved Search: Error message should not be displayed when running a locally saved search file","steps":[{"date":"2019-03-07 17:51:02","substeps":[{"date":"2019-03-07 17:51:02","message":"&quot;BasicSearchPage&quot; was loaded successfully","status":"passed"},{"date":"2019-03-07 17:51:03","message":"Clear textInput_Email.","status":"passed"},{"date":"2019-03-07 17:51:03","message":"textInput_Email  cleared.","status":"passed"},{"date":"2019-03-07 17:51:03","message":"Text of textInput_Email is .","status":"passed"},{"date":"2019-03-07 17:51:03","message":"Text of textInput_Email is wostesting47@gmail.com.","status":"passed"},{"date":"2019-03-07 17:51:03","message":"textInput_Email  'wostesting47@gmail.com' text was entered.","status":"passed"},{"date":"2019-03-07 17:51:03","message":"Clear textInput_Password.","status":"passed"},{"date":"2019-03-07 17:51:03","message":"textInput_Password  cleared.","status":"passed"},{"date":"2019-03-07 17:51:03","message":"Text of textInput_Password is .","status":"passed"},{"date":"2019-03-07 17:51:03","message":"Text of textInput_Password is wostesting@47.","status":"passed"},{"date":"2019-03-07 17:51:03","message":"textInput_Password  'wostesting@47' text was entered.","status":"passed"},{"date":"2019-03-07 17:51:26","message":"&quot;BasicSearchPage&quot; was loaded successfully","status":"passed"}],"title":"I sign in with account login &quot;wostesting47@gmail.com&quot; and password &quot;wostesting@47&quot;","status":"passed"},{"date":"2019-03-07 17:51:59","substeps":[{"date":"2019-03-07 17:51:59","status":"failed"}],"title":"I select &quot;saved searches&quot; item of WoS Toolbar menu","status":"failed"},{"date":"2019-03-07 17:50:43","title":"I choose a locally saved file from &quot;DII&quot; collection on &quot;Saved searches and alerts&quot; page","status":"skipped"},{"date":"2019-03-07 17:50:43","title":"I click on link &quot;Run Search&quot; on page &quot;View History&quot;","status":"skipped"},{"date":"2019-03-07 17:50:43","title":"I click on link &quot;Continue&quot; on page &quot;select time span and database&quot;","status":"skipped"},{"date":"2019-03-07 17:50:43","title":"I verify that &quot;Search History&quot; page is displayed","status":"skipped"}],"status":"failed"}}],"os":"Windows 10 10.0 amd64","ip":"10.10.246.5","browser":"firefox","name":"Feature_CCIssues","time":"2019-03-07 17:50:43","url":"https://tokenclient.wos-non-prod.oneplatform.build/tokens/QA1/client_ssl.cgi","targettestcycle":"WoS_5.32_R2_Staging"}}]