[{"testset":{"tests":[{"testcase":{"tag":"@TestCaseId(\"CheckMoLFile_002\")","time":"2019-06-18 09:46:13","title":"Check that corresponding MolFile is downloaded for the drugId passed in the request","steps":[{"date":"2019-06-18 09:46:13","title":"I am authenticated user accessing &quot;REST&quot; API","status":"passed"},{"date":"2019-06-18 09:46:13","StepAttachment":[{"mime":"TXT","content":"aHR0cDovL213YS51cy13ZXN0LTIuc3RhYmxlLmRldi5jb3J0ZWxsaXMuaW50LmNsYXJpdmF0ZS5jb206ODIwMC9tci9DaGVtaXN0cnlTSVNlcnZpY2UvdjEvbW9sRmlsZT9kcnVnSWQ9NzAwMDI="},{"mime":"TXT","content":""},{"mime":"TXT","content":""}],"title":"I pass a &quot;drugId = 70002 and operation = molFile and filename = mol.File&quot; as parameter to &quot;chemistrySIServiceRest&quot; operation","status":"passed"},{"date":"2019-06-18 09:46:14","substeps":[{"date":"2019-06-18 09:46:14","message":"This file doesnt exist in specified path &quot;mol.File&quot; has appeared","status":"failed"},{"date":"2019-06-18 09:46:14","message":"File not found","status":"failed"}],"title":"check the requested file is found in the following path &quot;mol.File&quot;","status":"failed"}],"status":"failed"}}],"os":"Windows Server 2008 R2 6.1 x86","ip":"10.152.84.170","name":"Feature_MolFile","time":"2019-06-18 09:46:13","url":"http://mwa.us-west-2.stable.dev.cortellis.int.clarivate.com","targettestcycle":"Smokes_Services_Stable_May24"}}]